BitbucketJenkins/__init__.py
BitbucketJenkins/bitbucket.py
BitbucketJenkins/client.py
BitbucketJenkins/error.py
BitbucketJenkins/jenkins.py
BitbucketJenkins-0.5.0.dist-info/LICENSE
BitbucketJenkins-0.5.0.dist-info/METADATA
BitbucketJenkins-0.5.0.dist-info/WHEEL
BitbucketJenkins-0.5.0.dist-info/top_level.txt
BitbucketJenkins-0.5.0.dist-info/RECORD
