Metadata-Version: 2.1
Name: BitbucketJenkins
Version: 0.5.0
Summary: A package for create Bitbucket project that integrate with Jenkins using Bitbucket team/project plugin
Home-page: https://github.com/ericsonrumuy7/BitbucketJenkins
Author: Ericson Rumuy
Author-email: ericsonrumuy@gmail.com
License: UNKNOWN
Platform: UNKNOWN
Classifier: Programming Language :: Python :: 2
Classifier: License :: OSI Approved :: MIT License
Classifier: Operating System :: OS Independent
Requires-Python: >=2.7
